{
    "nb_player": 1,
    "wait_nb_player": 1,
    "player_maitre": 0,
    "players": [
        {
            "id": 0,
            "statue": 1,
            "tour": 22,
            "bob_burnout": 0,
            "action_realisee": "",
            "tache_realisee": [],
            "credit_bonus": [
                0,
                0,
                0,
                0,
                0
            ],
            "piece_ferme": [
                [],
                [],
                [],
                [],
                []
            ],
            "effet_actif": "",
            "mission": [
                [
                    "R\u00e9parer une petite panne",
                    "Probl\u00e8me dehors",
                    "R\u00e9soudre un conflit"
                ],
                [
                    "Red\u00e9marrer le Wi-Fi",
                    "R\u00e9parer une petite panne",
                    "Mise \u00e0 jour syst\u00e8me"
                ],
                [
                    "Mise \u00e0 jour syst\u00e8me",
                    "S\u00e9curiser l'installation",
                    "Tester l\u2019\u00e9lectricit\u00e9"
                ]
            ],
            "mission_faite": [],
            "nb_player": 1,
            "wait_nb_player": 1,
            "player_maitre": 0
        }
    ]
}